py_parallel_processing/__init__.py
py_parallel_processing/__version__.py
py_parallel_processing/main.py
py_parallel_processing-0.4.2.dist-info/METADATA
py_parallel_processing-0.4.2.dist-info/WHEEL
py_parallel_processing-0.4.2.dist-info/top_level.txt
py_parallel_processing-0.4.2.dist-info/RECORD
