Metadata-Version: 2.1
Name: py-parallel-processing
Version: 0.4.2
Summary: ProcessPool은 여러 개의 프로세스를 생성하여 각각의 프로세스에서 함수를 병렬로 처리할 수 있도록 도와줍니다. tqdm은 진행상황 바(progress bar)를 표시하는 라이브러리로, total인자에 전체 반복횟수를 넣어주면 반복문 진행상황을 보여줍니다.
Home-page: UNKNOWN
Author: Hyeonjin Kim
Author-email: ilhj122@gmail.com
License: UNKNOWN
Platform: UNKNOWN
Classifier: Programming Language :: Python :: 3
Classifier: License :: OSI Approved :: MIT License
Classifier: Operating System :: OS Independent
Requires-Python: >=3.6
